{"cameraMode":{"drawMode":0,"name":"Shaded","section":"Shading Mode"},"sceneLighting":true,"audioPlay":false,"sceneViewState":{"m_AlwaysRefresh":false,"showFog":true,"showSkybox":true,"showFlares":true,"showImageEffects":true,"showParticleSystems":true,"showVisualEffectGraphs":true,"m_FxEnabled":true},"in2DMode":false,"pivot":{"x":-19.99810028076172,"y":6.886663436889648,"z":46.250423431396487},"rotation":{"x":-0.20096366107463838,"y":-0.6762648820877075,"z":0.222700834274292,"w":-0.6747857928276062},"size":5.808794021606445,"orthographic":false}